MANIFEST.in
README
setup.py
corunner/COPYING
corunner/Config.py
corunner/Config.pyc
corunner/FileTransporter.py
corunner/HeartBeatReceiver.py
corunner/HeartBeatReceiver.pyc
corunner/HeartBeatSender.py
corunner/ProcessNode.py
corunner/ProcessNode.pyc
corunner/TaskController.py
corunner/TaskExecutor.py
corunner/TaskExecutorProxy.py
corunner/TaskExecutorProxy.pyc
corunner/TestTimeout.py
corunner/__init__.py
corunner.egg-info/PKG-INFO
corunner.egg-info/SOURCES.txt
corunner.egg-info/dependency_links.txt
corunner.egg-info/entry_points.txt
corunner.egg-info/not-zip-safe
corunner.egg-info/top_level.txt
corunner/common/ArgumentParser.py
corunner/common/ArgumentParser.pyc
corunner/common/FileDispatcher.py
corunner/common/FileDispatcher.pyc
corunner/common/FileUtil.py
corunner/common/FileUtil.pyc
corunner/common/NetUtil.py
corunner/common/NetUtil.pyc
corunner/common/ShellUtil.py
corunner/common/ShellUtil.pyc
corunner/common/SimpleThreadPool.py
corunner/common/SimpleThreadPool.pyc
corunner/common/__init__.py
corunner/common/__init__.pyc
corunner/conf/corunner.properties
corunner/conf/logging.properties