Metadata-Version: 1.0
Name: corunner
Version: 1.0.7
Summary: A utility to transport files and execute at remote in prarallel
Home-page: https://sourceforge.net/projects/corunner
Author: zwsun
Author-email: sun33170161@gmail.com
License: Apache License V2.0
Platform: linux
